pyopencap/System.py
pyopencap/CAP.py
pyopencap/__init__.py
pyopencap/pyopencap_cpp.cpython-311-darwin.so
pyopencap/analysis/ColumbusParser.py
pyopencap/analysis/CAPTrajectory.py
pyopencap/analysis/__init__.py
pyopencap/.dylibs/libhdf5.310.5.1.dylib
pyopencap/.dylibs/libstdc++.6.dylib
pyopencap/.dylibs/libaec.0.1.3.dylib
pyopencap/.dylibs/libsz.2.0.1.dylib
pyopencap/.dylibs/libgcc_s.1.1.dylib
pyopencap/.dylibs/libgomp.1.dylib
pyopencap-1.2.7.dist-info/RECORD
pyopencap-1.2.7.dist-info/WHEEL
pyopencap-1.2.7.dist-info/top_level.txt
pyopencap-1.2.7.dist-info/METADATA
pyopencap-1.2.7.dist-info/licenses/LICENSE
