Metadata-Version: 2.4
Name: pyopencap
Version: 1.2.7
Summary: An open source package for metastable electronic states in molecules.
Author: James Gayvert
Author-email: jrg444@gmail.com
Project-URL: Source code, https://github.com/gayverjr/opencap
Project-URL: Documentation, https://gayverjropencap.readthedocs.io/en/latest/
License-File: LICENSE
Requires-Dist: numpy>=1.19
Requires-Dist: pandas>=1.3.5
Requires-Dist: scipy>=1.7.0
Dynamic: author
Dynamic: author-email
Dynamic: description
Dynamic: license-file
Dynamic: project-url
Dynamic: requires-dist
Dynamic: summary
